rummy_circl_otp.py
rummy_circl_otp-0.1.dist-info/METADATA
rummy_circl_otp-0.1.dist-info/WHEEL
rummy_circl_otp-0.1.dist-info/top_level.txt
rummy_circl_otp-0.1.dist-info/RECORD
