Metadata-Version: 2.1
Name: rummy-circl-otp
Version: 0.1
Requires-Dist: requests
